prometheus_qbittorrent_exporter-1.5.1.dist-info/METADATA
prometheus_qbittorrent_exporter-1.5.1.dist-info/WHEEL
prometheus_qbittorrent_exporter-1.5.1.dist-info/entry_points.txt
prometheus_qbittorrent_exporter-1.5.1.dist-info/licenses/LICENSE
qbittorrent_exporter/__init__.py
qbittorrent_exporter/exporter.py
prometheus_qbittorrent_exporter-1.5.1.dist-info/RECORD
