Metadata-Version: 2.1
Name: prometheus-qbittorrent-exporter
Version: 1.5.1
Summary: Prometheus exporter for qbittorrent
Keywords: prometheus qbittorrent
Author-Email: Esteban Sanchez <esteban.sanchez@gmail.com>
License: GPL-3.0
Project-URL: Homepage, https://github.com/esanchezm/prometheus-qbittorrent-exporter
Project-URL: Downloads, https://github.com/esanchezm/prometheus-qbittorrent-exporter/archive/1.5.1.tar.gz
Requires-Python: >=3.11
Requires-Dist: prometheus-client>=0.17.1
Requires-Dist: python-json-logger>=2.0.7
Requires-Dist: qbittorrent-api>=2023.9.53
